genpro/__init__.py
genpro/commands/__init__.py
genpro/model/__init__.py
genpro/model/prompt.py
genpro-0.1.2.dist-info/METADATA
genpro-0.1.2.dist-info/WHEEL
genpro-0.1.2.dist-info/entry_points.txt
genpro-0.1.2.dist-info/top_level.txt
genpro-0.1.2.dist-info/RECORD
