Metadata-Version: 2.1
Name: genpro
Version: 0.1.2
Author: Rajika Keminda
Author-email: rkeminda0@gmail.com
Keywords: cli,AI,python,project manager
Requires-Dist: click
Requires-Dist: python-dotenv
Requires-Dist: rich
Requires-Dist: openai
